abaxai_sdk/__init__.py
abaxai_sdk/streaming.py
abaxai_sdk/transcribing.py
abaxai_speech_client-0.1.2.dist-info/LICENSE
abaxai_speech_client-0.1.2.dist-info/METADATA
abaxai_speech_client-0.1.2.dist-info/WHEEL
abaxai_speech_client-0.1.2.dist-info/top_level.txt
abaxai_speech_client-0.1.2.dist-info/RECORD
