Metadata-Version: 2.1
Name: abaxai-speech-client
Version: 0.1.2
Summary: A Python3 client to connect and use Abax.AI Speech services
Home-page: https://github.com/ntuspeechlab/asr-client-scripts
Author: AbaxAI Developer
Author-email: tlvu@ntu.edu.sg
Project-URL: Bug Tracker, https://github.com/ntuspeechlab/asr-client-scripts/issues
Classifier: Programming Language :: Python :: 3
Classifier: License :: OSI Approved :: MIT License
Classifier: Operating System :: OS Independent
Requires-Python: >=3.6
License-File: LICENSE
